phyplot/__init__.py
phyplot/geo_scale.py
phyplot/interact.py
phyplot/plot_data.py
phyplot/plot_tree.py
phyplot/static.py
tests/__init__.py
tests/plot_test.py
phyplot-0.1.0.dist-info/LICENSE
phyplot-0.1.0.dist-info/METADATA
phyplot-0.1.0.dist-info/WHEEL
phyplot-0.1.0.dist-info/top_level.txt
phyplot-0.1.0.dist-info/RECORD
