Metadata-Version: 2.1
Name: phyplot
Version: 0.1.0
Summary: PhyloGrpah is a python package for plotting evolutionary trees and data.
Home-page: https://github.com/ChrisOrgan/phyplot
Author: Chris Organ & Andrew Meade
License: GNU General Public License v3.0
Keywords: plotting,graphs,evolution,phylogenetics,phylodynamics,comparative methods
Requires-Python: >=3.7
License-File: LICENSE
Requires-Dist: pandas (>=1.2.3)
Requires-Dist: scipy (>=1.6.3)
Requires-Dist: numpy (>=1.20.3)
Requires-Dist: ply (>=3.11)
